memestra/__init__.py
memestra/caching.py
memestra/docparse.py
memestra/memestra.py
memestra/nbmemestra.py
memestra/preprocessor.py
memestra/utils.py
memestra/version.py
memestra-0.2.1.dist-info/LICENSE
memestra-0.2.1.dist-info/METADATA
memestra-0.2.1.dist-info/WHEEL
memestra-0.2.1.dist-info/entry_points.txt
memestra-0.2.1.dist-info/top_level.txt
memestra-0.2.1.dist-info/RECORD
